hellopy/__init__.py
hellopy/hello.py
helloPackg_Thien-0.0.1.dist-info/METADATA
helloPackg_Thien-0.0.1.dist-info/WHEEL
helloPackg_Thien-0.0.1.dist-info/top_level.txt
helloPackg_Thien-0.0.1.dist-info/RECORD
