Metadata-Version: 2.1
Name: helloPackg-Thien
Version: 0.0.1
Summary: Hello package, Thien
Home-page: UNKNOWN
Author: Hoang Thien
Author-email: <thienho549@gmail.com>
License: UNKNOWN
Keywords: python,video,stream,video stream,camera stream,sockets
Platform: UNKNOWN
Classifier: Development Status :: 1 - Planning
Classifier: Intended Audience :: Developers
Classifier: Programming Language :: Python :: 3
Classifier: Operating System :: Unix
Classifier: Operating System :: MacOS :: MacOS X
Classifier: Operating System :: Microsoft :: Windows
